lne/__init__.py
lne/cli.py
lne/lne.py
lne-0.0.1.dist-info/AUTHORS.rst
lne-0.0.1.dist-info/LICENSE
lne-0.0.1.dist-info/METADATA
lne-0.0.1.dist-info/WHEEL
lne-0.0.1.dist-info/entry_points.txt
lne-0.0.1.dist-info/top_level.txt
lne-0.0.1.dist-info/RECORD
