Metadata-Version: 2.1
Name: lne
Version: 0.0.1
Summary: A Novel AI Model for Human Goal Achievement
Home-page: https://github.com/socra/lne
Author: Mike Morton
Author-email: mike@socra.com
License: MIT license
Keywords: lne
Classifier: Development Status :: 2 - Pre-Alpha
Classifier: Intended Audience :: Developers
Classifier: License :: OSI Approved :: MIT License
Classifier: Natural Language :: English
Classifier: Programming Language :: Python :: 3
Classifier: Programming Language :: Python :: 3.6
Classifier: Programming Language :: Python :: 3.7
Classifier: Programming Language :: Python :: 3.8
Requires-Python: >=3.6
License-File: LICENSE
License-File: AUTHORS.rst
